RUN_package/P_coeff.py
RUN_package/RUN-spyder.py
RUN_package/RUN.py
RUN_package/UV_coeff.py
RUN_package/__init__.py
RUN_package/boundaryDomain.py
RUN_package/correction.py
RUN_package/faceInterpolation.py
RUN_package/initialConditions.py
RUN_package/postProcessing.py
2D_Panel_CFD-0.0.1.dist-info/METADATA
2D_Panel_CFD-0.0.1.dist-info/WHEEL
2D_Panel_CFD-0.0.1.dist-info/top_level.txt
2D_Panel_CFD-0.0.1.dist-info/RECORD
