Metadata-Version: 2.1
Name: 2D-Panel-CFD
Version: 0.0.1
Summary: 2D_Panel CFD solver
Home-page: https://github.com/Fluidentity/2D_Panel-CFD
Author: Aman Sangal
Author-email: aman.sangal13@gmail.com
License: UNKNOWN
Project-URL: Bug Tracker, https://github.com/pypa/sampleproject/issues
Platform: UNKNOWN
Classifier: Programming Language :: Python :: 3
Classifier: License :: OSI Approved :: GNU General Public License v3 or later (GPLv3+)
Classifier: Operating System :: OS Independent
Requires-Python: >=3.6
